keggm/__init__.py
keggm/completem.py
keggm/completeness.py
keggm/enrichm.py
keggm/enrichment.py
keggm/kegg_core.py
keggm/keggm.py
keggm/keggscrape.py
keggm/multtestcorrection.py
keggm/plots.py
keggm/run_tests.py
keggm-0.0.1.data/scripts/keggm
keggm-0.0.1.dist-info/DESCRIPTION.rst
keggm-0.0.1.dist-info/LICENSE.txt
keggm-0.0.1.dist-info/METADATA
keggm-0.0.1.dist-info/RECORD
keggm-0.0.1.dist-info/WHEEL
keggm-0.0.1.dist-info/metadata.json
keggm-0.0.1.dist-info/top_level.txt
tests/__init__.py
tests/complete_test.py
tests/completem_test.py
tests/enrichm_test.py
tests/keggscrape_test.py
tests/plots_test.py
